Workbook

Sheet Break Analysis
A1: 差異拆解與獨立複核 Break Analysis
A3: 項目 | C3: 金額 | D3: 類型 | E3: 佐證/處理
A4: GL 總計 | C4: =Recon!F14
A5: 子帳 總計 | C5: =Recon!G14
A6: 總差異(GL−子帳) | C6: =C4-C5 | E6: =MV差合計
A8: FI-GB123 | C8: =Recon!H10 | D8: 誤報-時間差 | E8: TRD-9001 未交割買單,5/2 交割後消除
A9: FI-BUND | C9: =Recon!H9 | D9: 誤報-FX | E9: 0.003% < 0.05% 容差
A10: EQ-SPY | C10: =Recon!H8 | D10: 誤報-重分類 | E10: 僅分類欄不同,Qty/MV 一致
A11: 已解釋小計 | C11: =Recon!K14 | E11: (時間差+FX+重分類)
A13: EQ-VRT | C13: =Recon!H11 | D13: 真實 | E13: 子帳多2,500股,疑GL漏記買單
A14: FI-XYZ | C14: =Recon!H12 | D14: 真實 | E14: GL多1,000,000面額,疑GL未沖處分
A15: CA-USD | C15: =Recon!H13 | D15: 真實 | E15: 現金缺口600,000,查無佐證→升級
A16: 真實未解小計 | C16: =Recon!J14 | E16: 需處理
A18: 檢查：已解釋+真實=總差異 | C18: =IF(ROUND(Recon!J14+Recon!K14-(C4-C5),0)=0,"✓ tie-out","✗")

Sheet Recon
A1: GL ↔ 子帳 對帳 Reconciliation · Aurora Growth Fund III · 2026-04-30 (USD)
A2: GL=交易日基礎 / 子帳=交割日基礎(custody,外來)。Category 為複核分類(藍字輸入);Real/Explained 由公式拆解。
A4: Sec ID | B4: 資產類別 | C4: GL Qty | D4: Sub Qty | E4: Qty差 | F4: GL MV | G4: Sub MV | H4: MV差(GL−Sub) | I4: Category | J4: 真實break | K4: 已解釋
A5: EQ-AAPL | B5: Equity | C5: 50000 | D5: 50000 | E5: =C5-D5 | F5: 10000000 | G5: 10000000 | H5: =F5-G5 | I5: Match | J5: =IF(I5="REAL",H5,0) | K5: =IF(AND(I5<>"REAL",I5<>"Match"),H5,0)
A6: EQ-MSFT | B6: Equity | C6: 20000 | D6: 20000 | E6: =C6-D6 | F6: 8000000 | G6: 8000000 | H6: =F6-G6 | I6: Match | J6: =IF(I6="REAL",H6,0) | K6: =IF(AND(I6<>"REAL",I6<>"Match"),H6,0)
A7: EQ-NVDA | B7: Equity | C7: 10000 | D7: 10000 | E7: =C7-D7 | F7: 12000000 | G7: 12000000 | H7: =F7-G7 | I7: Match | J7: =IF(I7="REAL",H7,0) | K7: =IF(AND(I7<>"REAL",I7<>"Match"),H7,0)
A8: EQ-SPY | B8: Equity | C8: 5000 | D8: 5000 | E8: =C8-D8 | F8: 2000000 | G8: 2000000 | H8: =F8-G8 | I8: FP-Reclass | J8: =IF(I8="REAL",H8,0) | K8: =IF(AND(I8<>"REAL",I8<>"Match"),H8,0)
A9: FI-BUND | B9: Fixed Income | C9: 8333333 | D9: 8333333 | E9: =C9-D9 | F9: 9000000 | G9: 9000300 | H9: =F9-G9 | I9: FP-FX | J9: =IF(I9="REAL",H9,0) | K9: =IF(AND(I9<>"REAL",I9<>"Match"),H9,0)
A10: FI-GB123 | B10: Fixed Income | C10: 15500000 | D10: 15000000 | E10: =C10-D10 | F10: 15500000 | G10: 15000000 | H10: =F10-G10 | I10: FP-Timing | J10: =IF(I10="REAL",H10,0) | K10: =IF(AND(I10<>"REAL",I10<>"Match"),H10,0)
A11: EQ-VRT | B11: Equity | C11: 50000 | D11: 52500 | E11: =C11-D11 | F11: 5000000 | G11: 5250000 | H11: =F11-G11 | I11: REAL | J11: =IF(I11="REAL",H11,0) | K11: =IF(AND(I11<>"REAL",I11<>"Match"),H11,0)
A12: FI-XYZ | B12: Fixed Income | C12: 20000000 | D12: 19000000 | E12: =C12-D12 | F12: 20000000 | G12: 19000000 | H12: =F12-G12 | I12: REAL | J12: =IF(I12="REAL",H12,0) | K12: =IF(AND(I12<>"REAL",I12<>"Match"),H12,0)
A13: CA-USD | B13: Cash | C13: 0 | D13: 0 | E13: =C13-D13 | F13: 3000000 | G13: 2400000 | H13: =F13-G13 | I13: REAL | J13: =IF(I13="REAL",H13,0) | K13: =IF(AND(I13<>"REAL",I13<>"Match"),H13,0)
A14: 總計 Total | F14: =SUM(F5:F13) | G14: =SUM(G5:G13) | H14: =SUM(H5:H13) | J14: =SUM(J5:J13) | K14: =SUM(K5:K13)
A16: 檢查 1：MV差合計 = GL − 子帳 | H16: =IF(ROUND(H14-(F14-G14),0)=0,"✓","✗")
A17: 檢查 2：真實 + 已解釋 = MV差合計 | H17: =IF(ROUND(J14+K14-H14,0)=0,"✓","✗")

Sheet Escalation
A1: 升級清單 Escalation · 真實 break
A3: 優先 | B3: Sec | C3: 金額 | D3: 根因 | E3: 動作
A4: 1 | B4: CA-USD | C4: =Recon!H13 | D4: 現金缺口,不在未交割清單、非FX,查無佐證 | E4: 對銀行/保管流水,24h 內回覆;先排除錯帳/舞弊
A5: 2 | B5: FI-XYZ | C5: =Recon!H12 | D5: GL 多 1,000,000 面額;疑已處分/贖回保管已沖、GL 未沖 | E5: 調 XYZ 處分/贖回確認,GL 補沖減
A6: 3 | B6: EQ-VRT | C6: =Recon!H11 | D6: 子帳多 2,500 股;疑買單保管已入、GL 未入 | E6: 查 VRT 成交確認,GL 補入 2,500 股
A7: 監控 | B7: FI-GB123 | C7: =Recon!H10 | D7: 未交割買單(時間差) | E7: 2026-05-02 交割後覆核,差異應消除
