Workbook

Sheet NAV Bridge
A1: NAV 橋接 NAV Bridge · 2026-Q1
B3: 投資組合FV（GP報告） | C3: ='Valuation Review'!D9
B4: 現金 Cash | C4: 20000000
B5: 其他資產 Other Assets | C5: 5000000
B6: 應付費用 Accrued Liabilities | C6: -5000000
B7: ＝ NAV（as-reported） | C7: =C3+C4+C5+C6
B8: 減：Nova 不符政策上調（P2/P3） | C8: ='Valuation Review'!H6
B9: Zephyr stale（流程flag,未調金額） | C9: 0
B10: ＝ NAV（policy-adjusted） | C10: =C7+C8+C9
B13: 檢查：調整後投組 305M | C13: ='Valuation Review'!I9

Sheet Valuation Review
A1: GP 估值複核 Valuation Review（對照政策 P1–P4）· Aurora Growth Fund III · 2026-Q1
A3: 被投資公司 | B3: 成本 | C3: 上季FV | D3: GP報告FV | E3: 方法 | F3: 政策檢核(P1–P4) | G3: 判定 | H3: 政策調整 | I3: 調整後FV
A4: Helios Software | B4: 60000000 | C4: 90000000 | D4: 120000000 | E4: 可比公司 | F4: P2✓；P3待委員會核准文件 | G4: 有條件放行 | I4: =D4+N(H4) | J4: P3：確認是否高於2025-09輪價
A5: Orion Logistics | B5: 50000000 | C5: 55000000 | D5: 55000000 | E5: 近期交易 | F5: P1本季已複核✓ | G5: 放行 | I5: =D5+N(H5) | J5: 輪價漸老化(>9月)
A6: Nova Biotech | B6: 40000000 | C6: 40000000 | D6: 65000000 | E6: 管理層估計 | F6: ❌P2無方法/無觸發；❌P3無核准 | G6: 駁回上調 | H6: -25000000 | I6: =D6+N(H6) | J6: 撤回+25M至prior/cost 40M
A7: Titan Manufacturing | B7: 70000000 | C7: 60000000 | D7: 60000000 | E7: DCF | F7: P1✓ P2✓(下修,附DCF) | G7: 放行 | I7: =D7+N(H7) | J7: 已減損至成本以下
A8: Zephyr Retail | B8: 30000000 | C8: 30000000 | D8: 30000000 | E8: 成本法 | F8: ❌P1：4季未複核(stale) | G8: 需重新複核 | I8: =D8+N(H8) | J8: 流程flag；值未驗證
A9: 合計 Total | B9: =SUM(B4:B8) | C9: =SUM(C4:C8) | D9: =SUM(D4:D8) | H9: =SUM(H4:H8) | I9: =SUM(I4:I8)

Sheet Returns
A1: 報酬指標 Return Metrics
A3: 項目 | C3: Reported | D3: Adjusted
A4: 累計出資 Contributed | C4: 300000000 | D4: =C4
A5: 累計分配 Distributions | C5: 40000000 | D5: =C5
A6: NAV | C6: ='NAV Bridge'!C7 | D6: ='NAV Bridge'!C11
A7: TVPI | C7: =(C5+C6)/C4 | D7: =(D5+D6)/D4
A8: DPI | C8: =C5/C4 | D8: =D5/D4
A9: RVPI | C9: =C6/C4 | D9: =D6/D4
A11: 現金流 (XIRR)
A12: 日期 | B12: 事件 | C12: Reported | D12: Adjusted
A13: 44742 | B13: 出資 | C13: -100000000 | D13: -100000000
A14: 45107 | B14: 出資 | C14: -100000000 | D14: -100000000
A15: 45473 | B15: 出資 | C15: -100000000 | D15: -100000000
A16: 45838 | B16: 分配 | C16: 40000000 | D16: 40000000
A17: 46112 | B17: 期末NAV | C17: =C6 | D17: =D6
A19: Net IRR (XIRR) | C19: =XIRR(C13:C17,A13:A17) | D19: =XIRR(D13:D17,A13:A17)
A20: vs 8% hurdle | D20: =IF(D19<0.08,"❌ 低於hurdle","✓")

Sheet Pref Recompute
A1: 優先報酬獨立重算 Preferred Return Recompute（8% 複利）
A3: 利率 Rate | B3: 0.08
A4: 估值日 As-of | B4: 46112
A6: 現金流 | B6: 日期 | C6: 金額 | D6: 年數t | E6: FV@8%
A7: 出資1 | B7: 44742 | C7: 100000000 | D7: =YEARFRAC(B7,$B$4) | E7: =C7*(1+$B$3)^D7
A8: 出資2 | B8: 45107 | C8: 100000000 | D8: =YEARFRAC(B8,$B$4) | E8: =C8*(1+$B$3)^D8
A9: 出資3 | B9: 45473 | C9: 100000000 | D9: =YEARFRAC(B9,$B$4) | E9: =C9*(1+$B$3)^D9
A10: 分配 | B10: 45838 | C10: -40000000 | D10: =YEARFRAC(B10,$B$4) | E10: =C10*(1+$B$3)^D10
A12: FV 出資合計 | E12: =SUM(E7:E9)
A13: FV 分配 | E13: =E10
A14: 淨出資（300−40） | E14: 260000000
A15: ＝ 獨立重算優先報酬 | E15: =E12+E13-E14
A16: GP 包提供之 pref | E16: 35000000
A17: 差異（重算 − 提供） | E17: =E15-E16

Sheet Waterfall
A1: 收益分配 Waterfall（歐式/whole-fund；8% pref、100% catch-up、20% carry）
A3: 層級 / 情境 | B3: A: GP包(報告) | C3: B: 調整+pref35 | D3: C: 調整+獨立pref
A4: 總價值（分配+NAV） | B4: =Returns!C5+Returns!C6 | C4: =Returns!D5+Returns!D6 | D4: =Returns!D5+Returns!D6
A5: 承諾出資 Contributed | B5: =Returns!C4 | C5: =Returns!C4 | D5: =Returns!C4
A6: 優先報酬 Preferred | B6: 35000000 | C6: 35000000 | D6: ='Pref Recompute'!E15
A8: ① 返還出資 | B8: =MIN(B4,B5) | C8: =MIN(C4,C5) | D8: =MIN(D4,D5)
A9: 餘 after capital | B9: =B4-B8 | C9: =C4-C8 | D9: =D4-D8
A10: ② LP 優先報酬(付) | B10: =MIN(B9,B6) | C10: =MIN(C9,C6) | D10: =MIN(D9,D6)
A11: 餘 after pref | B11: =B9-B10 | C11: =C9-C10 | D11: =D9-D10
A12: ③ GP 追補 catch-up | B12: =MIN(B11,IF(B10>=B6,0.25*B6,0)) | C12: =MIN(C11,IF(C10>=C6,0.25*C6,0)) | D12: =MIN(D11,IF(D10>=D6,0.25*D6,0))
A13: 餘 after catch-up | B13: =B11-B12 | C13: =C11-C12 | D13: =D11-D12
A14: ④ 80/20 — LP 80% | B14: =B13*0.8 | C14: =C13*0.8 | D14: =D13*0.8
A15: ④ 80/20 — GP 20% | B15: =B13*0.2 | C15: =C13*0.2 | D15: =D13*0.2
A17: GP Carry 合計 | B17: =B12+B15 | C17: =C12+C15 | D17: =D12+D15
A18: LP 合計 | B18: =B8+B10+B14 | C18: =C8+C10+C14 | D18: =D8+D10+D14
A19: 檢查 LP+GP=總價值 | B19: =IF(ROUND(B17+B18-B4,0)=0,"✓","✗") | C19: =IF(ROUND(C17+C18-C4,0)=0,"✓","✗") | D19: =IF(ROUND(D17+D18-D4,0)=0,"✓","✗")
A21: 註：情境C用獨立重算pref(~69M);若調整後NAV未達 capital+pref → 無 catch-up、carry=0。pref基準須CCO對帳後定案。
