Workbook

Sheet Accruals & JEs
A1: 應計排程與草稿分錄 Accruals & Draft JEs · 2026-04（待 controller 核准，勿過帳）
A3: # | B3: 項目 | C3: 基礎 Basis | D3: 費用科目 | E3: 本期估列 | F3: 支援 Support
A4: A1 | B4: IT 服務(4月) | C4: 月帳單 ~75,000 | D4: 6300 資訊技術 | E4: 75000 | F4: 發票 2026-05-03,屬4月;發票入帳時沖回
A5: A2 | B5: 年度分紅 | C5: 獎金池 1,200,000 ÷ 12 | D5: 6000 薪酬 | E5: 100000 | F5: 薪酬計畫(按月攤)
A6: A3 | B6: FY2026 外部審計 | C6: 全年 300,000,~1/3 | D6: 6200 專業服務費 | E6: 100000 | F6: 審計委任書(累計估列,已入帳0)
D7: 合計 | E7: =SUM(E4:E6)
A9: 草稿分錄 Draft Journal Entries
A10: JE | B10: 借方 Dr | C10: 金額 | D10: 貸方 Cr | E10: 金額 | F10: Memo
A11: JE-A1 | B11: Dr 6300 資訊技術 | C11: 75000 | D11: Cr 2100 應付費用 | E11: 75000 | F11: IT 服務 2026-04 估列(自動沖回)
A12: JE-A2 | B12: Dr 6000 薪酬 | C12: 100000 | D12: Cr 2100 應付費用 | E12: 100000 | F12: 分紅 2026-04 按月估列
A13: JE-A3 | B13: Dr 6200 專業服務費 | C13: 100000 | D13: Cr 2100 應付費用 | E13: 100000 | F13: FY2026 審計累計估列
B14: JE 合計(Dr=Cr 檢查) | C14: =SUM(C11:C13) | E14: =SUM(E11:E13) | F14: ← Dr 應 = Cr ✓

Sheet Trial Balance
A1: 試算表 Trial Balance — Aurora Capital Management LLC · 2026-04 (USD)
A3: 科目 | B3: 名稱 | C3: 類別 | D3: Dr/Cr | E3: 上月 03 | F3: 本月 04 pre | G3: 應計調整 | H3: 結帳後 post | J3: Dr(post) | K3: Cr(post)
A4: 1000 | B4: 現金 Cash | C4: 資產 | D4: Dr | E4: 8000000 | F4: 7550000 | H4: =F4+N(G4) | J4: =IF(D4="Dr",H4,0) | K4: =IF(D4="Cr",H4,0)
A5: 1100 | B5: 應收管理費 | C5: 資產 | D5: Dr | E5: 3000000 | F5: 3200000 | H5: =F5+N(G5) | J5: =IF(D5="Dr",H5,0) | K5: =IF(D5="Cr",H5,0)
A6: 1200 | B6: 預付費用 | C6: 資產 | D6: Dr | E6: 600000 | F6: 600000 | H6: =F6+N(G6) | J6: =IF(D6="Dr",H6,0) | K6: =IF(D6="Cr",H6,0)
A7: 1500 | B7: 固定資產淨額 | C7: 資產 | D7: Dr | E7: 1400000 | F7: 1350000 | H7: =F7+N(G7) | J7: =IF(D7="Dr",H7,0) | K7: =IF(D7="Cr",H7,0)
A8: 2000 | B8: 應付帳款 | C8: 負債 | D8: Cr | E8: 900000 | F8: 1100000 | H8: =F8+N(G8) | J8: =IF(D8="Dr",H8,0) | K8: =IF(D8="Cr",H8,0)
A9: 2100 | B9: 應付費用 | C9: 負債 | D9: Cr | E9: 1200000 | F9: 1000000 | G9: 275000 | H9: =F9+N(G9) | J9: =IF(D9="Dr",H9,0) | K9: =IF(D9="Cr",H9,0)
A10: 2200 | B10: 遞延收入 | C10: 負債 | D10: Cr | E10: 500000 | F10: 400000 | H10: =F10+N(G10) | J10: =IF(D10="Dr",H10,0) | K10: =IF(D10="Cr",H10,0)
A11: 3000 | B11: 成員資本 | C11: 權益 | D11: Cr | E11: 8000000 | F11: 8000000 | H11: =F11+N(G11) | J11: =IF(D11="Dr",H11,0) | K11: =IF(D11="Cr",H11,0)
A12: 3100 | B12: 期初保留盈餘 | C12: 權益 | D12: Cr | E12: 2000000 | F12: 2000000 | H12: =F12+N(G12) | J12: =IF(D12="Dr",H12,0) | K12: =IF(D12="Cr",H12,0)
A13: 4000 | B13: 管理費收入 | C13: 收入 | D13: Cr | E13: 6300000 | F13: 8500000 | H13: =F13+N(G13) | J13: =IF(D13="Dr",H13,0) | K13: =IF(D13="Cr",H13,0)
A14: 4100 | B14: 其他收入 | C14: 收入 | D14: Cr | E14: 300000 | F14: 380000 | H14: =F14+N(G14) | J14: =IF(D14="Dr",H14,0) | K14: =IF(D14="Cr",H14,0)
A15: 6000 | B15: 薪酬 | C15: 費用 | D15: Dr | E15: 4500000 | F15: 6000000 | G15: 100000 | H15: =F15+N(G15) | J15: =IF(D15="Dr",H15,0) | K15: =IF(D15="Cr",H15,0)
A16: 6100 | B16: 租金 | C16: 費用 | D16: Dr | E16: 600000 | F16: 800000 | H16: =F16+N(G16) | J16: =IF(D16="Dr",H16,0) | K16: =IF(D16="Cr",H16,0)
A17: 6200 | B17: 專業服務費 | C17: 費用 | D17: Dr | E17: 400000 | F17: 750000 | G17: 100000 | H17: =F17+N(G17) | J17: =IF(D17="Dr",H17,0) | K17: =IF(D17="Cr",H17,0)
A18: 6300 | B18: 資訊技術 | C18: 費用 | D18: Dr | E18: 300000 | F18: 400000 | G18: 75000 | H18: =F18+N(G18) | J18: =IF(D18="Dr",H18,0) | K18: =IF(D18="Cr",H18,0)
A19: 6400 | B19: 差旅 | C19: 費用 | D19: Dr | E19: 150000 | F19: 350000 | H19: =F19+N(G19) | J19: =IF(D19="Dr",H19,0) | K19: =IF(D19="Cr",H19,0)
A20: 6500 | B20: 其他營運費用 | C20: 費用 | D20: Dr | E20: 250000 | F20: 330000 | H20: =F20+N(G20) | J20: =IF(D20="Dr",H20,0) | K20: =IF(D20="Cr",H20,0)
A21: 6600 | B21: 折舊 | C21: 費用 | D21: Dr | E21: 0 | F21: 50000 | H21: =F21+N(G21) | J21: =IF(D21="Dr",H21,0) | K21: =IF(D21="Cr",H21,0)
B22: 合計 / 平衡檢查 | E22: =SUM(E4:E21) | F22: =SUM(F4:F21) | G22: =SUM(G4:G21) | H22: =SUM(H4:H21) | J22: =SUM(J4:J21) | K22: =SUM(K4:K21)
B23: 借貸差額 Dr−Cr (post) | J23: =J22-K22 | K23: ← 應為 0 ✓
B25: YTD 淨利(post) = 收入 − 費用 | H25: =(H13+H14)-SUM(H15:H21)
B26: （pre-close 淨利對照） | H26: =(F13+F14)-SUM(F15:F21)

Sheet Roll-forward 2100
A1: 應付費用 (2100) 結轉 Roll-forward · 2026-04
B3: 期初餘額(2026-03 月底) | C3: 1200000
B4: 減：4月支付/沖回 | C4: -200000
B5: ＝ 結帳前餘額 | C5: =C3+C4
B6: 加：新估列(A1+A2+A3) | C6: ='Accruals & JEs'!E7
B7: ＝ 期末餘額(post-close) | C7: =C5+C6
B10: Foot check：期初+變動=期末 | C10: =IF(C7=C3+C4+C6,"✓ 對得上","✗")
B11: 對試算表 2100 post-close 一致？ | C11: ='Trial Balance'!H9

Sheet Variance
A1: 差異說明 Variance（當月 vs 前3月跑率；門檻 >5%）· post-close
A3: 科目 | B3: 名稱 | C3: 前YTD | D3: 後YTD | E3: 當月 | F3: 月跑率 | G3: 當月vs跑率 | H3: 判讀
A4: 6000 | B4: 薪酬 | C4: ='Trial Balance'!E15 | D4: ='Trial Balance'!H15 | E4: =D4-C4 | F4: =C4/3 | G4: =IF(F4=0,"n/a",E4/F4-1) | H4: 分紅估列 A2 驅動;跑率持平。已解釋
A5: 6100 | B5: 租金 | C5: ='Trial Balance'!E16 | D5: ='Trial Balance'!H16 | E5: =D5-C5 | F5: =C5/3 | G5: =IF(F5=0,"n/a",E5/F5-1) | H5: 純 YTD 機械增加,符合跑率。正常
A6: 6200 | B6: 專業服務費 | C6: ='Trial Balance'!E17 | D6: ='Trial Balance'!H17 | E6: =D6-C6 | F6: =C6/3 | G6: =IF(F6=0,"n/a",E6/F6-1) | H6: ⚠ 審計估列+其餘~$350k 超跑率,來源不明→需查
A7: 6300 | B7: 資訊技術 | C7: ='Trial Balance'!E18 | D7: ='Trial Balance'!H18 | E7: =D7-C7 | F7: =C7/3 | G7: =IF(F7=0,"n/a",E7/F7-1) | H7: 多為 A1 估列;其餘符合跑率。已解釋
A8: 6400 | B8: 差旅 | C8: ='Trial Balance'!E19 | D8: ='Trial Balance'!H19 | E8: =D8-C8 | F8: =C8/3 | G8: =IF(F8=0,"n/a",E8/F8-1) | H8: ⚠ 當月為跑率4倍,來源不明→需查
A9: 6500 | B9: 其他營運 | C9: ='Trial Balance'!E20 | D9: ='Trial Balance'!H20 | E9: =D9-C9 | F9: =C9/3 | G9: =IF(F9=0,"n/a",E9/F9-1) | H9: 符合跑率。正常
A10: 6600 | B10: 折舊 | C10: ='Trial Balance'!E21 | D10: ='Trial Balance'!H21 | E10: =D10-C10 | F10: =C10/3 | G10: =IF(F10=0,"n/a",E10/F10-1) | H10: ⚠ 1–3月為0、4月才提,時點/補提疑慮→需查
