Workbook

Sheet Football Field
A1: 估值區間彙總 Football Field — Vertiv (VRT)
A2: 每股 US$;現價 $320;示意控制報價 $400(+25%)
A4: 估值法 | B4: 低端 $ | C4: 高端 $ | D4: 中點 $ | E4: vs現價 | F4: 說明
A5: 52週交易區間 | B5: 130 | C5: 400 | D5: ~$265 | E5: =(130+400)/2/320-1 | F5: 市場情緒(示意)
A6: 分析師目標價 | B6: 300 | C6: 450 | D6: ~$375 | E6: =(300+450)/2/320-1 | F6: 賣方共識(示意);BofA等
A7: 同業比較 Comps | B7: 198 | C7: 320 | D7: $259 | E7: =(198+320)/2/320-1 | F7: 25–40x FY26E EBITDA
A8: 先例交易 | B8: 158 | C8: 223 | D8: $191 | E8: =(158+223)/2/320-1 | F8: 20–28x;純散熱控制交易
A9: DCF | B9: 100 | C9: 245 | D9: $173 | E9: =(100+245)/2/320-1 | F9: 永續法~$102 / 出場22x~$245
A10: LBO ability-to-pay | B10: 168 | C10: 196 | D10: $182 | E10: =(168+196)/2/320-1 | F10: 20–25% IRR 反推
A12: 現價 Current | B12: 320
A13: 示意報價 Offer | B13: 400
A15: 核心結論:現價 $320 已位於多數內在/交易法之上;控制溢價(→~$400)僅情緒類參考(52週高/樂觀PT)可及。
A16: 內在(DCF)、先例交易與 LBO ability-to-pay 一致指向 $158–$245——收購 VRT 需對已偏貴的價格再付溢價,且 LBO 規模/倍數不可行。

Sheet LBO
A1: Vertiv (VRT) — 示意槓桿收購 ILLUSTRATIVE LBO
A2: US$bn(每股除外)| 藍=輸入 黑=公式 紫=同頁連結 | 示意性:VRT 規模 ~$122bn,傳統 LBO 不可行,本表僅示範報酬數學
A4: 假設 ASSUMPTIONS | E4: 資金來源與用途 SOURCES & USES
A5: 報價/股 Offer ($) | B5: 400 | E5: 用途 Uses | G5: 來源 Sources
A6: 對現價溢價 | B6: =B5/320-1 | E6: 購買股權 | F6: =B5*B7 | G6: 新負債 | H6: =B10*B9
A7: 股數 (bn) | B7: 0.382 | E7: 再融資淨負債 | F7: =B8 | G7: 發起人股權(plug) | H7: =F9-H6
A8: 現有淨負債 | B8: 1.9 | E8: 交易費用 | F8: =F6*B13
A9: FY26E EBITDA | B9: 3.11 | E9: 用途合計 | F9: =SUM(F6:F8) | G9: 來源合計 | H9: =H6+H7
A10: 進場槓桿 (x EBITDA) | B10: 6 | E10: 進場 EV | F10: =F6+B8
A11: 負債利率 | B11: 0.08 | E11: 進場 EV/EBITDA | F11: =F10/B9
A12: 稅率 | B12: 0.21
A13: 交易費用 %股權 | B13: 0.025
A14: 出場 EV/EBITDA | B14: 22
A16: 營運模型 OPERATING MODEL (FY27→FY31E)
A17: 項目 | C17: 進場FY26 | D17: FY27E | E17: FY28E | F17: FY29E | G17: FY30E | H17: FY31E
A18: 營收成長 % | D18: 0.22 | E18: 0.16 | F18: 0.12 | G18: 0.09 | H18: 0.07
A19: 營收 Revenue | C19: 13.75 | D19: =C19*(1+D18) | E19: =D19*(1+E18) | F19: =E19*(1+F18) | G19: =F19*(1+G18) | H19: =G19*(1+H18)
A20: EBITDA 利潤率 % | D20: 0.235 | E20: 0.245 | F20: 0.255 | G20: 0.26 | H20: 0.27
A21: EBITDA | D21: =D19*D20 | E21: =E19*E20 | F21: =F19*F20 | G21: =G19*G20 | H21: =H19*H20
A22: 減：D&A(2.6%) | D22: =D19*0.026 | E22: =E19*0.026 | F22: =F19*0.026 | G22: =G19*0.026 | H22: =H19*0.026
A23: EBIT | D23: =D21-D22 | E23: =E21-E22 | F23: =F21-F22 | G23: =G21-G22 | H23: =H21-H22
A24: 減：Capex(2.3%) | D24: =D19*0.023 | E24: =E19*0.023 | F24: =F19*0.023 | G24: =G19*0.023 | H24: =H19*0.023
A25: 減：現金稅 | D25: =D23*$B$12 | E25: =E23*$B$12 | F25: =F23*$B$12 | G25: =G23*$B$12 | H25: =H23*$B$12
A26: 減：ΔNWC(8%) | D26: =(D19-C19)*0.08 | E26: =(E19-D19)*0.08 | F26: =(F19-E19)*0.08 | G26: =(G19-F19)*0.08 | H26: =(H19-G19)*0.08
A28: 負債期初 | D28: =H6 | E28: =D31 | F28: =E31 | G28: =F31 | H28: =G31
A29: 利息(期初×利率) | D29: =D28*$B$11 | E29: =E28*$B$11 | F29: =F28*$B$11 | G29: =G28*$B$11 | H29: =H28*$B$11
A30: FCF 可償債 | D30: =D21-D24-D25-D29-D26 | E30: =E21-E24-E25-E29-E26 | F30: =F21-F24-F25-F29-F26 | G30: =G21-G24-G25-G29-G26 | H30: =H21-H24-H25-H29-H26
A31: 負債期末(掃債) | D31: =MAX(D28-D30,0) | E31: =MAX(E28-E30,0) | F31: =MAX(F28-F30,0) | G31: =MAX(G28-G30,0) | H31: =MAX(H28-H30,0)
A33: 出場與報酬 EXIT & RETURNS
A34: 出場 EBITDA (FY31) | B34: =H21 | D34: Ability-to-Pay(反推進場)
A35: 出場 EV (×倍數) | B35: =B34*B14 | D35: 目標 IRR | E35: 進場股權 | F35: 進場 EV | G35: 每股 $
A36: 減：出場淨負債 | B36: =H31 | D36: 0.15 | E36: =$B$37/(1+D36)^5 | F36: =E36+$H$6 | G36: =(F36-$B$8)/$B$7
A37: 出場股權價值 | B37: =B35-B36 | D37: 0.2 | E37: =$B$37/(1+D37)^5 | F37: =E37+$H$6 | G37: =(F37-$B$8)/$B$7
A38: 發起人進場股權 | B38: =H7 | D38: 0.25 | E38: =$B$37/(1+D38)^5 | F38: =E38+$H$6 | G38: =(F38-$B$8)/$B$7
A39: MOIC | B39: =B37/B38
A40: IRR (5年) | B40: =(B37/B38)^(1/5)-1 | D40: 解讀:示意 $400 報價 IRR ~0–1%(不可行);要達 20–25% IRR 進場價需 ~$168–$196,即現價 $320 的大幅折讓。

Sheet Comps
A1: 同業比較 Trading Comps（散熱/電力基礎設施,資料約 2026/6,估計值）
A3: 公司 | B3: 代碼 | C3: 市值$bn | D3: 營收YoY | E3: EBITDA利潤率 | F3: Fwd P/E | G3: EV/EBITDA | H3: 純度
A4: Vertiv ★ | B4: VRT | C4: ~122 | D4: +28% | E4: ~23% | F4: ~46x | G4: ~40-51x | H4: 純(高)
A5: nVent | B5: NVT | C5: ~28 | D5: +11% | E5: ~20% | F5: ~35x | G5: ~32x | H5: 多元
A6: Schneider | B6: SU.PA | C6: ~160 | D6: +5% | E6: ~19% | F6: ~28x | G6: ~21x | H6: 多元
A7: Delta 台達電 | B7: 2308 | C7: ~187 | D7: +33% | E7: ~18% | F7: ~46x | G7: n/a | H7: 多元
A8: Supermicro | B8: SMCI | C8: ~18 | D8: +123% | E8: ~6% | F8: ~9x | G8: ~16x | H8: OEM
A9: nVent/同業中位 | B9: — | C9: — | D9: — | E9: — | F9: ~30x | G9: ~26x | H9: —
A11: Comps 隱含 VRT 區間(套 25–40x FY26E EBITDA $3.1bn):每股約 $198–$320。VRT 本身即同業最高倍數,溢價反映 AI 純度與龍頭地位。

Sheet Precedent Txns
A1: 先例交易 Precedent Transactions（資料中心散熱/基礎設施 2022–2026）
A3: 日期 | B3: 買方 | C3: 標的 | D3: EV (US$) | E3: EV/EBITDA | F3: EV/Revenue | G3: 來源旗標
A4: 2026-03 | B4: Ecolab | C4: CoolIT Systems | D4: $4.75bn | E4: 29x NTM / 24x'27E | F4: ~8.6x | G4: 揭露/估
A5: 2025-12 | B5: Eaton | C5: Boyd Thermal | D5: $9.5bn | E5: 22.5x '26E | F5: ~5.6x | G5: 揭露/估
A6: 2024-10 | B6: Schneider | C6: Motivair(75%) | D6: $0.85bn | E6: n/a | F6: 中個位數(rev) | G6: 揭露(質化)
A7: 2025-11 | B7: Vertiv | C7: PurgeRite | D7: ~$1.0bn | E7: ~10x '26E(含綜效) | F7: n/a | G7: 揭露
A8: 2023-04 | B8: Carrier | C8: Viessmann(參考) | D8: ~$13bn | E8: ~13x(綜效) | F8: ~3.0x | G8: 揭露(非DC)
A9: 2025-03 | B9: nVent | C9: Avail EPG(電力) | D9: $0.975bn | E9: n/a | F9: ~2.6x | G9: 估
A10: 2023 | B10: KKR | C10: CoolIT(前手) | D10: 未揭露 | E10: n/a | F10: n/a | G10: KKR 出場 ~15x
A12: 純散熱控制交易 EV/EBITDA 區間 ~10x–29x(前瞻);套 20–28x 於 VRT FY26E EBITDA → 每股約 $158–$223。
A13: 注意:CoolIT/Boyd 為『前瞻』倍數且標的成長更快、規模更小;VRT 規模大、成長較緩,直接類比會高估。Carrier/Viessmann 為 HVAC,僅作規模參考。

Sheet DCF Summary
A1: DCF 估值彙總（詳見 Vertiv_VRT_DCF.xlsx）
A3: 方法 | B3: WACC | C3: 終值 | D3: 隱含每股 | E3: 備註
A4: 永續成長法 | B4: 11.4% | C4: g=3.5% | D4: ~$102 | E4: 紀律性;終值占EV偏高
A5: 出場倍數法 | B5: 11.4% | C5: 22x EBITDA | D5: ~$245 | E5: 較寬鬆
A6: 區間 | B6: — | C6: — | D6: $100–$245 | E6: DCF 中樞遠低於現價 $320
A8: 結論:以紀律性 DCF,VRT 內在價值中樞約 $100–$245,顯著低於現價 $320——市場已 price in 高度完美成長。

Sheet Synergies & Sensitivity
A1: 綜效 Ability-to-Pay 與 IRR 敏感度（連結 LBO 分頁）
A2: US$bn(每股除外)| 綠=連結 LBO | 假設:出場淨負債保守維持基準(不計綜效額外掃債)
A4: 綜效 Ability-to-Pay（@ 20% IRR,出場 22x）
A5: 綜效(run-rate, $bn) | B5: 出場EBITDA | C5: 出場股權 | D5: 進場股權@20% | E5: 進場EV | F5: 每股 $
A6: 0 | B6: =LBO!$H$21+A6 | C6: =B6*LBO!$B$14-LBO!$H$31 | D6: =C6/(1+0.2)^5 | E6: =D6+LBO!$H$6 | F6: =(E6-LBO!$B$8)/LBO!$B$7
A7: 0.5 | B7: =LBO!$H$21+A7 | C7: =B7*LBO!$B$14-LBO!$H$31 | D7: =C7/(1+0.2)^5 | E7: =D7+LBO!$H$6 | F7: =(E7-LBO!$B$8)/LBO!$B$7
A8: 1 | B8: =LBO!$H$21+A8 | C8: =B8*LBO!$B$14-LBO!$H$31 | D8: =C8/(1+0.2)^5 | E8: =D8+LBO!$H$6 | F8: =(E8-LBO!$B$8)/LBO!$B$7
A9: 1.5 | B9: =LBO!$H$21+A9 | C9: =B9*LBO!$B$14-LBO!$H$31 | D9: =C9/(1+0.2)^5 | E9: =D9+LBO!$H$6 | F9: =(E9-LBO!$B$8)/LBO!$B$7
A10: 2 | B10: =LBO!$H$21+A10 | C10: =B10*LBO!$B$14-LBO!$H$31 | D10: =C10/(1+0.2)^5 | E10: =D10+LBO!$H$6 | F10: =(E10-LBO!$B$8)/LBO!$B$7
A12: 解讀:即使綜效 $2.0bn(≈進場 EBITDA 的 64%),@20% IRR 的進場價仍僅 ~$243,低於現價 $320。
A13: 反推:要在 20% IRR 下 justify $320,需 run-rate 綜效約 $5.3bn(≈進場 EBITDA 1.7 倍)——不切實際。
A15: IRR 敏感度:報價/股 × 出場 EV/EBITDA（中心=基準 $400 / 22x）
A16: 報價↓ / 倍數→ | B16: 18 | C16: 20 | D16: 22 | E16: 24 | F16: 26
A17: 320 | B17: =((18*LBO!$H$21-LBO!$H$31)/($A17*LBO!$B$7*(1+LBO!$B$13)+LBO!$B$8-LBO!$H$6))^(1/5)-1 | C17: =((20*LBO!$H$21-LBO!$H$31)/($A17*LBO!$B$7*(1+LBO!$B$13)+LBO!$B$8-LBO!$H$6))^(1/5)-1 | D17: =((22*LBO!$H$21-LBO!$H$31)/($A17*LBO!$B$7*(1+LBO!$B$13)+LBO!$B$8-LBO!$H$6))^(1/5)-1 | E17: =((24*LBO!$H$21-LBO!$H$31)/($A17*LBO!$B$7*(1+LBO!$B$13)+LBO!$B$8-LBO!$H$6))^(1/5)-1 | F17: =((26*LBO!$H$21-LBO!$H$31)/($A17*LBO!$B$7*(1+LBO!$B$13)+LBO!$B$8-LBO!$H$6))^(1/5)-1
A18: 360 | B18: =((18*LBO!$H$21-LBO!$H$31)/($A18*LBO!$B$7*(1+LBO!$B$13)+LBO!$B$8-LBO!$H$6))^(1/5)-1 | C18: =((20*LBO!$H$21-LBO!$H$31)/($A18*LBO!$B$7*(1+LBO!$B$13)+LBO!$B$8-LBO!$H$6))^(1/5)-1 | D18: =((22*LBO!$H$21-LBO!$H$31)/($A18*LBO!$B$7*(1+LBO!$B$13)+LBO!$B$8-LBO!$H$6))^(1/5)-1 | E18: =((24*LBO!$H$21-LBO!$H$31)/($A18*LBO!$B$7*(1+LBO!$B$13)+LBO!$B$8-LBO!$H$6))^(1/5)-1 | F18: =((26*LBO!$H$21-LBO!$H$31)/($A18*LBO!$B$7*(1+LBO!$B$13)+LBO!$B$8-LBO!$H$6))^(1/5)-1
A19: 400 | B19: =((18*LBO!$H$21-LBO!$H$31)/($A19*LBO!$B$7*(1+LBO!$B$13)+LBO!$B$8-LBO!$H$6))^(1/5)-1 | C19: =((20*LBO!$H$21-LBO!$H$31)/($A19*LBO!$B$7*(1+LBO!$B$13)+LBO!$B$8-LBO!$H$6))^(1/5)-1 | D19: =((22*LBO!$H$21-LBO!$H$31)/($A19*LBO!$B$7*(1+LBO!$B$13)+LBO!$B$8-LBO!$H$6))^(1/5)-1 | E19: =((24*LBO!$H$21-LBO!$H$31)/($A19*LBO!$B$7*(1+LBO!$B$13)+LBO!$B$8-LBO!$H$6))^(1/5)-1 | F19: =((26*LBO!$H$21-LBO!$H$31)/($A19*LBO!$B$7*(1+LBO!$B$13)+LBO!$B$8-LBO!$H$6))^(1/5)-1
A20: 440 | B20: =((18*LBO!$H$21-LBO!$H$31)/($A20*LBO!$B$7*(1+LBO!$B$13)+LBO!$B$8-LBO!$H$6))^(1/5)-1 | C20: =((20*LBO!$H$21-LBO!$H$31)/($A20*LBO!$B$7*(1+LBO!$B$13)+LBO!$B$8-LBO!$H$6))^(1/5)-1 | D20: =((22*LBO!$H$21-LBO!$H$31)/($A20*LBO!$B$7*(1+LBO!$B$13)+LBO!$B$8-LBO!$H$6))^(1/5)-1 | E20: =((24*LBO!$H$21-LBO!$H$31)/($A20*LBO!$B$7*(1+LBO!$B$13)+LBO!$B$8-LBO!$H$6))^(1/5)-1 | F20: =((26*LBO!$H$21-LBO!$H$31)/($A20*LBO!$B$7*(1+LBO!$B$13)+LBO!$B$8-LBO!$H$6))^(1/5)-1
A21: 480 | B21: =((18*LBO!$H$21-LBO!$H$31)/($A21*LBO!$B$7*(1+LBO!$B$13)+LBO!$B$8-LBO!$H$6))^(1/5)-1 | C21: =((20*LBO!$H$21-LBO!$H$31)/($A21*LBO!$B$7*(1+LBO!$B$13)+LBO!$B$8-LBO!$H$6))^(1/5)-1 | D21: =((22*LBO!$H$21-LBO!$H$31)/($A21*LBO!$B$7*(1+LBO!$B$13)+LBO!$B$8-LBO!$H$6))^(1/5)-1 | E21: =((24*LBO!$H$21-LBO!$H$31)/($A21*LBO!$B$7*(1+LBO!$B$13)+LBO!$B$8-LBO!$H$6))^(1/5)-1 | F21: =((26*LBO!$H$21-LBO!$H$31)/($A21*LBO!$B$7*(1+LBO!$B$13)+LBO!$B$8-LBO!$H$6))^(1/5)-1
A23: 中心格($400/22x)應≈LBO 分頁 IRR(~0.7%)。即便出場 26x + 報價降至 $320,IRR 仍遠低於 PE 門檻(~20–25%)。
